asmr18/__init__.py
asmr18/cli.py
asmr18/database.py
asmr18/downloader.py
asmr18/logger.py
asmr18/utils.py
asmr18-0.1.5.dist-info/licenses/LICENSE
asmr18-0.1.5.dist-info/METADATA
asmr18-0.1.5.dist-info/WHEEL
asmr18-0.1.5.dist-info/entry_points.txt
asmr18-0.1.5.dist-info/top_level.txt
asmr18-0.1.5.dist-info/RECORD
